Metadata-Version: 2.1
Name: thingsprompt
Version: 1.0.11
Summary: ThingsDB Prompt
Home-page: https://github.com/thingsdb/ThingsPrompt
Author: Jeroen van der Heijden
Author-email: jeroen@cesbit.com
License: GPLv3
Keywords: database connector prompt thingsdb
Classifier: Development Status :: 4 - Beta
Classifier: Intended Audience :: Developers
Classifier: Topic :: Database :: Front-Ends 
Classifier: License :: OSI Approved :: MIT License
Classifier: Programming Language :: Python :: 3.8
Classifier: Programming Language :: Python :: 3.9
Classifier: Programming Language :: Python :: 3.10
Classifier: Programming Language :: Python :: 3.11
Classifier: Programming Language :: Python :: 3.12
License-File: LICENSE
Requires-Dist: setproctitle
Requires-Dist: python-thingsdb
Requires-Dist: prompt-toolkit
Requires-Dist: pygments
